{
    "grid": [
        [
            "ㅎ",
            "ㅣ",
            "ㅣ",
            "ㄱ"
        ],
        [
            "ㅍ",
            "ㅈ",
            "ㅗ",
            "ㅂ"
        ],
        [
            "ㅣ",
            "ㄹ",
            "ㅣ",
            "ㅇ"
        ],
        [
            "ㄹ",
            "ㅇ",
            "ㅎ",
            "ㅡ"
        ]
    ],
    "bonuses": [
        [
            1,
            0,
            0,
            0
        ],
        [
            0,
            0,
            0,
            0
        ],
        [
            0,
            0,
            0,
            0
        ],
        [
            0,
            1,
            0,
            0
        ]
    ],
    "words": [
        {
            "word": "졸",
            "common": 0
        },
        {
            "word": "기집",
            "common": 0
        },
        {
            "word": "이이",
            "common": 0
        },
        {
            "word": "괴리",
            "common": 0
        },
        {
            "word": "뢰비",
            "common": 0
        },
        {
            "word": "잎",
            "common": 1
        },
        {
            "word": "흥복",
            "common": 0
        },
        {
            "word": "흥",
            "common": 0
        },
        {
            "word": "로질",
            "common": 0
        },
        {
            "word": "로기",
            "common": 0
        },
        {
            "word": "오질",
            "common": 0
        },
        {
            "word": "곱",
            "common": 0
        },
        {
            "word": "뢰지",
            "common": 0
        },
        {
            "word": "지복",
            "common": 0
        },
        {
            "word": "이롭",
            "common": 0
        },
        {
            "word": "고일",
            "common": 0
        },
        {
            "word": "의질",
            "common": 0
        },
        {
            "word": "집",
            "common": 1
        },
        {
            "word": "질로",
            "common": 0
        },
        {
            "word": "외직",
            "common": 0
        },
        {
            "word": "외리",
            "common": 0
        },
        {
            "word": "오리일",
            "common": 0
        },
        {
            "word": "보기",
            "common": 0
        },
        {
            "word": "보일",
            "common": 0
        },
        {
            "word": "의족",
            "common": 0
        },
        {
            "word": "필링",
            "common": 0
        },
        {
            "word": "공비",
            "common": 0
        },
        {
            "word": "이외",
            "common": 1
        },
        {
            "word": "오",
            "common": 1
        },
        {
            "word": "비조",
            "common": 0
        },
        {
            "word": "리이",
            "common": 0
        },
        {
            "word": "피죄",
            "common": 0
        },
        {
            "word": "골",
            "common": 1
        },
        {
            "word": "욍",
            "common": 0
        },
        {
            "word": "비질",
            "common": 0
        },
        {
            "word": "기",
            "common": 0
        },
        {
            "word": "고지리",
            "common": 0
        },
        {
            "word": "오지",
            "common": 0
        },
        {
            "word": "릴",
            "common": 0
        },
        {
            "word": "필롱",
            "common": 0
        },
        {
            "word": "고빙",
            "common": 0
        },
        {
            "word": "이록",
            "common": 0
        },
        {
            "word": "집괴",
            "common": 0
        },
        {
            "word": "조이",
            "common": 0
        },
        {
            "word": "비",
            "common": 1
        },
        {
            "word": "고집",
            "common": 1
        },
        {
            "word": "질입",
            "common": 0
        },
        {
            "word": "종빙",
            "common": 0
        },
        {
            "word": "복",
            "common": 1
        },
        {
            "word": "일족",
            "common": 0
        },
        {
            "word": "올",
            "common": 1
        },
        {
            "word": "피이",
            "common": 0
        },
        {
            "word": "희종",
            "common": 0
        },
        {
            "word": "좁",
            "common": 0
        },
        {
            "word": "피조리",
            "common": 0
        },
        {
            "word": "공",
            "common": 1
        },
        {
            "word": "비흥",
            "common": 0
        },
        {
            "word": "집오리",
            "common": 0
        },
        {
            "word": "입",
            "common": 1
        },
        {
            "word": "기종",
            "common": 0
        },
        {
            "word": "지",
            "common": 1
        },
        {
            "word": "리오",
            "common": 0
        },
        {
            "word": "직보",
            "common": 0
        },
        {
            "word": "비올",
            "common": 0
        },
        {
            "word": "의보",
            "common": 0
        },
        {
            "word": "의죄",
            "common": 0
        },
        {
            "word": "일죄",
            "common": 0
        },
        {
            "word": "지리",
            "common": 0
        },
        {
            "word": "리",
            "common": 0
        },
        {
            "word": "고지",
            "common": 0
        },
        {
            "word": "조비",
            "common": 0
        },
        {
            "word": "옥비",
            "common": 0
        },
        {
            "word": "의조",
            "common": 0
        },
        {
            "word": "힝",
            "common": 0
        },
        {
            "word": "피질",
            "common": 0
        },
        {
            "word": "잎집",
            "common": 0
        },
        {
            "word": "리비",
            "common": 0
        },
        {
            "word": "징",
            "common": 0
        },
        {
            "word": "이립",
            "common": 0
        },
        {
            "word": "히로",
            "common": 0
        },
        {
            "word": "일흥",
            "common": 0
        },
        {
            "word": "죄리",
            "common": 0
        },
        {
            "word": "힐",
            "common": 0
        },
        {
            "word": "일로",
            "common": 0
        },
        {
            "word": "희",
            "common": 0
        },
        {
            "word": "볼링",
            "common": 1
        },
        {
            "word": "록",
            "common": 0
        },
        {
            "word": "이죄",
            "common": 0
        },
        {
            "word": "일지필",
            "common": 0
        },
        {
            "word": "지골",
            "common": 0
        },
        {
            "word": "보리",
            "common": 1
        },
        {
            "word": "이집",
            "common": 0
        },
        {
            "word": "입공",
            "common": 0
        },
        {
            "word": "골필",
            "common": 0
        },
        {
            "word": "리조",
            "common": 0
        },
        {
            "word": "집올히",
            "common": 0
        },
        {
            "word": "이직",
            "common": 0
        },
        {
            "word": "외비",
            "common": 0
        },
        {
            "word": "이오",
            "common": 0
        },
        {
            "word": "비족",
            "common": 0
        },
        {
            "word": "필종",
            "common": 0
        },
        {
            "word": "입고",
            "common": 0
        },
        {
            "word": "필흥",
            "common": 0
        },
        {
            "word": "옳이",
            "common": 0
        },
        {
            "word": "비록",
            "common": 0
        },
        {
            "word": "피",
            "common": 1
        },
        {
            "word": "볼",
            "common": 1
        },
        {
            "word": "로지",
            "common": 0
        },
        {
            "word": "필지",
            "common": 0
        },
        {
            "word": "롱",
            "common": 0
        },
        {
            "word": "질뢰",
            "common": 0
        },
        {
            "word": "봉",
            "common": 0
        },
        {
            "word": "의이",
            "common": 0
        },
        {
            "word": "잉비",
            "common": 0
        },
        {
            "word": "이리",
            "common": 1
        },
        {
            "word": "비괴",
            "common": 0
        },
        {
            "word": "옥",
            "common": 0
        },
        {
            "word": "오집",
            "common": 0
        },
        {
            "word": "이비",
            "common": 0
        },
        {
            "word": "흥보",
            "common": 0
        },
        {
            "word": "집일",
            "common": 0
        },
        {
            "word": "로",
            "common": 0
        },
        {
            "word": "의비",
            "common": 0
        },
        {
            "word": "피집",
            "common": 0
        },
        {
            "word": "고립",
            "common": 0
        },
        {
            "word": "비옥",
            "common": 0
        },
        {
            "word": "비공",
            "common": 0
        },
        {
            "word": "일",
            "common": 1
        },
        {
            "word": "고징",
            "common": 0
        },
        {
            "word": "지비",
            "common": 0
        },
        {
            "word": "피지",
            "common": 0
        },
        {
            "word": "오기",
            "common": 0
        },
        {
            "word": "조리",
            "common": 0
        },
        {
            "word": "지오",
            "common": 0
        },
        {
            "word": "리졸",
            "common": 0
        },
        {
            "word": "이종",
            "common": 0
        },
        {
            "word": "비종",
            "common": 0
        },
        {
            "word": "직봉",
            "common": 0
        },
        {
            "word": "공히",
            "common": 0
        },
        {
            "word": "질일",
            "common": 0
        },
        {
            "word": "필",
            "common": 0
        },
        {
            "word": "피로",
            "common": 1
        },
        {
            "word": "희보",
            "common": 0
        },
        {
            "word": "조",
            "common": 1
        },
        {
            "word": "괴",
            "common": 0
        },
        {
            "word": "지로",
            "common": 0
        },
        {
            "word": "흐",
            "common": 0
        },
        {
            "word": "이옥",
            "common": 0
        },
        {
            "word": "지뢰",
            "common": 0
        },
        {
            "word": "보지",
            "common": 0
        },
        {
            "word": "빙",
            "common": 0
        },
        {
            "word": "이조",
            "common": 0
        },
        {
            "word": "이일",
            "common": 0
        },
        {
            "word": "지록",
            "common": 0
        },
        {
            "word": "집의",
            "common": 0
        },
        {
            "word": "보잉",
            "common": 0
        },
        {
            "word": "기지",
            "common": 0
        },
        {
            "word": "비이",
            "common": 0
        },
        {
            "word": "입기",
            "common": 0
        },
        {
            "word": "리질",
            "common": 0
        },
        {
            "word": "이봉",
            "common": 0
        },
        {
            "word": "지롱",
            "common": 0
        },
        {
            "word": "지골피",
            "common": 0
        },
        {
            "word": "일리",
            "common": 0
        },
        {
            "word": "이",
            "common": 1
        },
        {
            "word": "피일",
            "common": 0
        },
        {
            "word": "필집",
            "common": 0
        },
        {
            "word": "공희",
            "common": 0
        },
        {
            "word": "죄이",
            "common": 0
        },
        {
            "word": "비고",
            "common": 0
        },
        {
            "word": "질록",
            "common": 0
        },
        {
            "word": "리로",
            "common": 0
        },
        {
            "word": "괴지",
            "common": 0
        },
        {
            "word": "이롱",
            "common": 0
        },
        {
            "word": "기징",
            "common": 0
        },
        {
            "word": "이로이",
            "common": 0
        },
        {
            "word": "기질",
            "common": 0
        },
        {
            "word": "희로",
            "common": 0
        },
        {
            "word": "흐이",
            "common": 0
        },
        {
            "word": "고리",
            "common": 0
        },
        {
            "word": "지고리",
            "common": 0
        },
        {
            "word": "히",
            "common": 0
        },
        {
            "word": "이로",
            "common": 0
        },
        {
            "word": "피리",
            "common": 0
        },
        {
            "word": "집기",
            "common": 0
        },
        {
            "word": "기조",
            "common": 0
        },
        {
            "word": "조일",
            "common": 0
        },
        {
            "word": "외이",
            "common": 0
        },
        {
            "word": "질",
            "common": 1
        },
        {
            "word": "히피족",
            "common": 0
        },
        {
            "word": "골질",
            "common": 0
        },
        {
            "word": "리보",
            "common": 0
        },
        {
            "word": "보",
            "common": 0
        },
        {
            "word": "뢰",
            "common": 0
        },
        {
            "word": "오링",
            "common": 0
        },
        {
            "word": "지옥",
            "common": 0
        },
        {
            "word": "이징",
            "common": 0
        },
        {
            "word": "비오리",
            "common": 0
        },
        {
            "word": "희롱",
            "common": 0
        },
        {
            "word": "일일",
            "common": 0
        },
        {
            "word": "지봉",
            "common": 0
        },
        {
            "word": "이피",
            "common": 0
        },
        {
            "word": "지괴",
            "common": 0
        },
        {
            "word": "록비",
            "common": 0
        },
        {
            "word": "기비",
            "common": 0
        },
        {
            "word": "이족",
            "common": 0
        },
        {
            "word": "외피질",
            "common": 0
        },
        {
            "word": "빅",
            "common": 0
        },
        {
            "word": "외피",
            "common": 0
        },
        {
            "word": "졸필",
            "common": 0
        },
        {
            "word": "링",
            "common": 0
        },
        {
            "word": "리지",
            "common": 0
        },
        {
            "word": "비로",
            "common": 0
        },
        {
            "word": "옳",
            "common": 0
        },
        {
            "word": "피뢰",
            "common": 0
        },
        {
            "word": "외",
            "common": 1
        },
        {
            "word": "보직",
            "common": 0
        },
        {
            "word": "짚",
            "common": 0
        },
        {
            "word": "괴질",
            "common": 0
        },
        {
            "word": "봉희",
            "common": 0
        },
        {
            "word": "피조",
            "common": 0
        },
        {
            "word": "공빙",
            "common": 0
        },
        {
            "word": "지고",
            "common": 0
        },
        {
            "word": "의졸",
            "common": 0
        },
        {
            "word": "잉",
            "common": 0
        },
        {
            "word": "지일",
            "common": 0
        },
        {
            "word": "외집",
            "common": 0
        },
        {
            "word": "일록",
            "common": 0
        },
        {
            "word": "이복",
            "common": 0
        },
        {
            "word": "힐지",
            "common": 0
        },
        {
            "word": "일이",
            "common": 0
        },
        {
            "word": "고입",
            "common": 0
        },
        {
            "word": "일지",
            "common": 0
        },
        {
            "word": "기졸",
            "common": 0
        },
        {
            "word": "기봉",
            "common": 0
        },
        {
            "word": "징비",
            "common": 0
        },
        {
            "word": "조의",
            "common": 0
        },
        {
            "word": "올히",
            "common": 0
        },
        {
            "word": "로이",
            "common": 0
        },
        {
            "word": "고이",
            "common": 0
        },
        {
            "word": "비오",
            "common": 0
        },
        {
            "word": "일종",
            "common": 1
        },
        {
            "word": "깁",
            "common": 0
        },
        {
            "word": "고비",
            "common": 0
        },
        {
            "word": "지필",
            "common": 0
        },
        {
            "word": "오지리",
            "common": 0
        },
        {
            "word": "히피",
            "common": 0
        },
        {
            "word": "외지",
            "common": 0
        },
        {
            "word": "보이",
            "common": 0
        },
        {
            "word": "일질",
            "common": 0
        },
        {
            "word": "일롱",
            "common": 0
        },
        {
            "word": "괴이",
            "common": 0
        },
        {
            "word": "핑",
            "common": 0
        },
        {
            "word": "일직",
            "common": 0
        },
        {
            "word": "의지",
            "common": 1
        },
        {
            "word": "집고",
            "common": 0
        },
        {
            "word": "로직",
            "common": 0
        },
        {
            "word": "지외",
            "common": 0
        },
        {
            "word": "골지",
            "common": 0
        },
        {
            "word": "로비",
            "common": 0
        },
        {
            "word": "뵐",
            "common": 0
        },
        {
            "word": "립",
            "common": 0
        },
        {
            "word": "볼일",
            "common": 1
        },
        {
            "word": "빚",
            "common": 1
        },
        {
            "word": "일히",
            "common": 0
        },
        {
            "word": "조입",
            "common": 0
        },
        {
            "word": "괴링",
            "common": 0
        },
        {
            "word": "의뢰",
            "common": 0
        },
        {
            "word": "로입",
            "common": 0
        },
        {
            "word": "깆",
            "common": 0
        },
        {
            "word": "오리",
            "common": 1
        },
        {
            "word": "리징",
            "common": 0
        },
        {
            "word": "필조",
            "common": 0
        },
        {
            "word": "의리",
            "common": 0
        },
        {
            "word": "의",
            "common": 0
        },
        {
            "word": "기보",
            "common": 0
        },
        {
            "word": "지피",
            "common": 0
        },
        {
            "word": "집이",
            "common": 0
        },
        {
            "word": "의집",
            "common": 0
        },
        {
            "word": "힐조",
            "common": 0
        },
        {
            "word": "이보",
            "common": 0
        },
        {
            "word": "이지",
            "common": 0
        },
        {
            "word": "로빙",
            "common": 0
        },
        {
            "word": "리외",
            "common": 0
        },
        {
            "word": "비리",
            "common": 0
        },
        {
            "word": "피립",
            "common": 0
        },
        {
            "word": "고",
            "common": 0
        },
        {
            "word": "이졸",
            "common": 0
        },
        {
            "word": "족",
            "common": 0
        },
        {
            "word": "희오",
            "common": 0
        },
        {
            "word": "으",
            "common": 0
        },
        {
            "word": "종비",
            "common": 0
        },
        {
            "word": "일조",
            "common": 0
        },
        {
            "word": "이질",
            "common": 0
        },
        {
            "word": "옵",
            "common": 0
        },
        {
            "word": "비지",
            "common": 0
        },
        {
            "word": "죄",
            "common": 1
        },
        {
            "word": "뵈",
            "common": 0
        },
        {
            "word": "고의",
            "common": 0
        },
        {
            "word": "의복",
            "common": 1
        },
        {
            "word": "곶",
            "common": 0
        },
        {
            "word": "지이",
            "common": 0
        },
        {
            "word": "종",
            "common": 1
        },
        {
            "word": "왹",
            "common": 0
        },
        {
            "word": "리피",
            "common": 0
        },
        {
            "word": "힁",
            "common": 0
        },
        {
            "word": "직",
            "common": 0
        },
        {
            "word": "필로",
            "common": 0
        },
        {
            "word": "일희",
            "common": 0
        },
        {
            "word": "조기",
            "common": 1
        },
        {
            "word": "비골",
            "common": 0
        },
        {
            "word": "리직",
            "common": 0
        },
        {
            "word": "오비",
            "common": 0
        },
        {
            "word": "외일",
            "common": 0
        },
        {
            "word": "보링",
            "common": 0
        },
        {
            "word": "오직",
            "common": 1
        },
        {
            "word": "피롱",
            "common": 0
        },
        {
            "word": "지보",
            "common": 0
        },
        {
            "word": "일필",
            "common": 0
        },
        {
            "word": "골집",
            "common": 0
        },
        {
            "word": "올리",
            "common": 0
        },
        {
            "word": "조빙",
            "common": 0
        },
        {
            "word": "희비",
            "common": 0
        },
        {
            "word": "필히",
            "common": 0
        },
        {
            "word": "지공",
            "common": 0
        },
        {
            "word": "고질",
            "common": 0
        },
        {
            "word": "골히",
            "common": 0
        },
        {
            "word": "질리",
            "common": 0
        },
        {
            "word": "입옥",
            "common": 0
        },
        {
            "word": "기지리",
            "common": 0
        },
        {
            "word": "일집",
            "common": 0
        },
        {
            "word": "조립",
            "common": 0
        }
    ]
}